xsigma.py
xsigmamodules/all.py
xsigmamodules/Analytics.cp312-win_amd64.pyd
xsigmamodules/Analytics.pyi
xsigmamodules/Core.cp312-win_amd64.pyd
xsigmamodules/Core.pyi
xsigmamodules/generate_pyi.py
xsigmamodules/Instrument.cp312-win_amd64.pyd
xsigmamodules/Instrument.pyi
xsigmamodules/Market.cp312-win_amd64.pyd
xsigmamodules/Market.pyi
xsigmamodules/Math.cp312-win_amd64.pyd
xsigmamodules/Math.pyi
xsigmamodules/py.typed
xsigmamodules/Random.cp312-win_amd64.pyd
xsigmamodules/Random.pyi
xsigmamodules/Util.cp312-win_amd64.pyd
xsigmamodules/Util.pyi
xsigmamodules/Vectorization.cp312-win_amd64.pyd
xsigmamodules/Vectorization.pyi
xsigmamodules/__init__.py
xsigmamodules/common/helper.py
xsigmamodules/common/instrument.py
xsigmamodules/common/__init__.py
xsigmamodules/market/market_data.py
xsigmamodules/market/__init__.py
xsigmamodules/simulation/simulation.py
xsigmamodules/simulation/__init__.py
xsigmamodules/test/BlackBox.py
xsigmamodules/test/Testing.py
xsigmamodules/test/__init__.py
xsigmamodules/util/misc.py
xsigmamodules/util/numpy_support.py
xsigmamodules/util/object_converter.py
xsigmamodules/util/xsigmaConstants.py
xsigmamodules/util/xsigmaMethodParser.py
xsigmamodules/util/__init__.py
xsigmamodules/xlwing/hartman_watson_template.py
xsigmamodules/xlwing/sabr_template.py
xsigmamodules/xlwing/__init__.py
xsigma_mkl-1.1.3.dev0.dist-info/DELVEWHEEL
xsigma_mkl-1.1.3.dev0.dist-info/LICENSE
xsigma_mkl-1.1.3.dev0.dist-info/METADATA
xsigma_mkl-1.1.3.dev0.dist-info/RECORD
xsigma_mkl-1.1.3.dev0.dist-info/top_level.txt
xsigma_mkl-1.1.3.dev0.dist-info/WHEEL
xsigma_mkl.libs/Analytics-3c072e44dfe2bf958b7acc4b7f7a0c74.dll
xsigma_mkl.libs/Core-c278014ab1abb2053857e26ae4330d6e.dll
xsigma_mkl.libs/Instrument-5430f71f2371e43abe6f04dd311ee8ad.dll
xsigma_mkl.libs/Market-ec637144412b170d12e149e3b07e850e.dll
xsigma_mkl.libs/Math-f9fed480e4893b628e506dab960a26cf.dll
xsigma_mkl.libs/msvcp140-e6779840cfaa5e7215d08812d831e17d.dll
xsigma_mkl.libs/PDE-a00ecfd10f5b3348f090031620beeca8.dll
xsigma_mkl.libs/Random-54098fe161dde6f225673817d2b9e4d4.dll
xsigma_mkl.libs/Serialization-8608924f6b4ea88f206cad62a31c242a.dll
xsigma_mkl.libs/svml_dispmd-17cb47cc1ab754ecbe9558a0c05e643a.dll
xsigma_mkl.libs/tbb12-1f5424895e3c6942c3f40fa2bccc6e03.dll
